dime/__init__.py
dime/client.py
dime/dimeb.py
dime/json.py
dime_client-0.0.1.dist-info/LICENSE
dime_client-0.0.1.dist-info/METADATA
dime_client-0.0.1.dist-info/WHEEL
dime_client-0.0.1.dist-info/top_level.txt
dime_client-0.0.1.dist-info/RECORD
