Metadata-Version: 2.1
Name: dime-client
Version: 0.0.1
Summary: DiME client for Python
Home-page: https://github.com/zmalkmus/dimedev
Author: Zack Malkmus
Author-email: zmalkmus@vols.utk.edu
License: GNU License V3
Classifier: Programming Language :: Python :: 3
Classifier: License :: OSI Approved :: GNU General Public License v3 (GPLv3)
Classifier: Operating System :: OS Independent
License-File: LICENSE
Requires-Dist: numpy
